README.txt
setup.py
collective/__init__.py
collective.langMailHost.egg-info/PKG-INFO
collective.langMailHost.egg-info/SOURCES.txt
collective.langMailHost.egg-info/dependency_links.txt
collective.langMailHost.egg-info/entry_points.txt
collective.langMailHost.egg-info/namespace_packages.txt
collective.langMailHost.egg-info/not-zip-safe
collective.langMailHost.egg-info/paster_plugins.txt
collective.langMailHost.egg-info/requires.txt
collective.langMailHost.egg-info/top_level.txt
collective/langMailHost/__init__.py
collective/langMailHost/configure.zcml
collective/langMailHost/interfaces.py
collective/langMailHost/skins.zcml
collective/langMailHost/tool.py
collective/langMailHost/version.txt
collective/langMailHost/Extensions/__init__.py
collective/langMailHost/Extensions/install.py
collective/langMailHost/adapter/__init__.py
collective/langMailHost/adapter/configure.zcml
collective/langMailHost/adapter/mail.py
collective/langMailHost/adapter/send.py
collective/langMailHost/browser/__init__.py
collective/langMailHost/browser/configure.zcml
collective/langMailHost/browser/encoding.py
collective/langMailHost/profiles/default/propertiestool.xml
collective/langMailHost/profiles/default/skins.xml
collective/langMailHost/profiles/default/toolset.xml
collective/langMailHost/profiles/uninstall/propertiestool.xml
collective/langMailHost/profiles/uninstall/skins.xml
collective/langMailHost/skins/collective_langMailHost_scripts/send_feedback_site.cpy
collective/langMailHost/skins/collective_langMailHost_scripts/send_feedback_site.cpy.metadata
collective/langMailHost/tests/__init__.py
collective/langMailHost/tests/base.py
collective/langMailHost/tests/test_functional.py
collective/langMailHost/tests/test_setup.py
collective/langMailHost/tests/functional/adapter.txt
collective/langMailHost/tests/functional/send.txt
docs/HISTORY.txt
docs/LICENSE.GPL
docs/LICENSE.txt