Metadata-Version: 1.0
Name: collective.langMailHost
Version: 0.3.4
Summary: This package aims to provide language dependent character set for sending emails form Plone site.
Home-page: http://pypi.python.org/pypi/collective.langMailHost
Author: Taito Horiuchi
Author-email: taito.horiuchi@gmail.com
License: GPL
Platform: UNKNOWN
Classifier: Framework :: Plone
Classifier: Programming Language :: Python
Classifier: Topic :: Software Development :: Libraries :: Python Modules
